[
  {
    "pt-pt": "policial",
    "nl": "politie",
    "en": "police (officer)",
    "fr": "policier",
    "de": "Polizei",
    "it": "poliziotto",
    "pl": "policyjny",
    "pt-br": "policial",
    "ro": "polițist",
    "ru": "полицейский",
    "es": "policial",
    "uk": "поліцейський",
    "word_type": "adjective",
    "positive": "policial",
    "comparative": "mais policial",
    "superlative": "o mais policial",
    "key": "police-officer"
  },
  {
    "pt-pt": "rapidamente",
    "nl": "snel",
    "en": "quickly",
    "fr": "rapidement",
    "de": "schnell",
    "it": "rapidamente",
    "pl": "szybko",
    "pt-br": "rapidamente",
    "ro": "rapid",
    "ru": "быстро",
    "es": "rápidamente",
    "uk": "швидко",
    "word_type": "adverb",
    "key": "quickly"
  },
  {
    "pt-pt": "o reino",
    "nl": "het koninkrijk",
    "en": "kingdom",
    "fr": "le royaume",
    "de": "das Königreich",
    "it": "il regno",
    "pl": "królestwo",
    "pt-br": "o reino",
    "ro": "regatul",
    "ru": "королевство",
    "es": "el reino",
    "uk": "королівство",
    "word_type": "noun",
    "plural_form": "os reinos",
    "gender": "masculine",
    "key": "kingdom"
  },
  {
    "pt-pt": "o sistema",
    "nl": "het systeem",
    "en": "system",
    "fr": "le système",
    "de": "das System",
    "it": "il sistema",
    "pl": "system",
    "pt-br": "o sistema",
    "ro": "sistemul",
    "ru": "система",
    "es": "el sistema",
    "uk": "система",
    "word_type": "noun",
    "plural_form": "os sistemas",
    "gender": "masculine",
    "key": "system"
  },
  {
    "pt-pt": "o ato",
    "nl": "de daad",
    "en": "act",
    "fr": "l'acte",
    "de": "die Tat",
    "it": "l'atto",
    "pl": "czyn",
    "pt-br": "o ato",
    "ro": "actul",
    "ru": "акт",
    "es": "el acto",
    "uk": "акт",
    "word_type": "noun",
    "plural_form": "os atos",
    "gender": "masculine",
    "key": "act"
  },
  {
    "pt-pt": "a categoria",
    "nl": "de categorie",
    "en": "category",
    "fr": "la catégorie",
    "de": "die Kategorie",
    "it": "la categoria",
    "pl": "kategoria",
    "pt-br": "a categoria",
    "ro": "categoria",
    "ru": "категория",
    "es": "la categoría",
    "uk": "категорія",
    "word_type": "noun",
    "plural_form": "as categorias",
    "gender": "feminine",
    "key": "category"
  },
  {
    "pt-pt": "o episódio",
    "nl": "de aflevering",
    "en": "episode",
    "fr": "l'épisode",
    "de": "die Episode",
    "it": "l'episodio",
    "pl": "odcinek",
    "pt-br": "o episódio",
    "ro": "episodul",
    "ru": "эпизод",
    "es": "el episodio",
    "uk": "епізод",
    "word_type": "noun",
    "plural_form": "os episódios",
    "gender": "masculine",
    "key": "episode"
  },
  {
    "pt-pt": "a espécie",
    "nl": "de soort",
    "en": "species",
    "fr": "l'espèce",
    "de": "die Art",
    "it": "la specie",
    "pl": "gatunek",
    "pt-br": "a espécie",
    "ro": "specia",
    "ru": "вид",
    "es": "la especie",
    "uk": "вид",
    "word_type": "noun",
    "plural_form": "as espécies",
    "gender": "feminine",
    "key": "species"
  },
  {
    "pt-pt": "os irmãos",
    "nl": "de broers (en zussen)",
    "en": "siblings",
    "fr": "les frères (et sœurs)",
    "de": "die Geschwister",
    "it": "i fratelli",
    "pl": "rodzeństwo",
    "pt-br": "os irmãos",
    "ro": "frații",
    "ru": "братья (и сёстры)",
    "es": "los hermanos",
    "uk": "брати (і сестри)",
    "word_type": "noun",
    "gender": "masculine",
    "key": "siblings"
  },
  {
    "pt-pt": "a parceria",
    "nl": "het partnerschap",
    "en": "partnership",
    "fr": "le partenariat",
    "de": "die Partnerschaft",
    "it": "la partnership",
    "pl": "partnerstwo",
    "pt-br": "a parceria",
    "ro": "parteneriatul",
    "ru": "партнерство",
    "es": "la asociación",
    "uk": "партнерство",
    "word_type": "noun",
    "plural_form": "as parcerias",
    "gender": "feminine",
    "key": "partnership"
  },
  {
    "pt-pt": "o prefeito",
    "nl": "de burgemeester",
    "en": "mayor",
    "fr": "le maire",
    "de": "der Bürgermeister",
    "it": "il sindaco",
    "pl": "burmistrz",
    "pt-br": "o prefeito",
    "ro": "primarul",
    "ru": "мэр",
    "es": "el alcalde",
    "uk": "мер",
    "word_type": "noun",
    "plural_form": "os prefeitos",
    "gender": "masculine",
    "key": "mayor"
  },
  {
    "pt-pt": "pós",
    "nl": "na",
    "en": "post",
    "fr": "post",
    "de": "nach",
    "it": "post",
    "pl": "po",
    "pt-br": "pós",
    "ro": "post",
    "ru": "пост",
    "es": "pos",
    "uk": "пост",
    "word_type": "preposition",
    "key": "post"
  },
  {
    "pt-pt": "realizado",
    "nl": "gerealiseerd",
    "en": "realized",
    "fr": "réalisé",
    "de": "realisiert",
    "it": "realizzato",
    "pl": "zrealizowany",
    "pt-br": "realizado",
    "ro": "realizat",
    "ru": "реализованный",
    "es": "realizado",
    "uk": "реалізований",
    "word_type": "adjective",
    "positive": "realizado",
    "comparative": "mais realizado",
    "superlative": "o mais realizado",
    "key": "realized"
  },
  {
    "pt-pt": "o redor",
    "nl": "de omgeving",
    "en": "surroundings",
    "fr": "l'entourage",
    "de": "die Umgebung",
    "it": "l'intorno",
    "pl": "okolica",
    "pt-br": "o redor",
    "ro": "împrejurimile",
    "ru": "окрестности",
    "es": "el alrededor",
    "uk": "околиці",
    "word_type": "noun",
    "plural_form": "os redores",
    "gender": "masculine",
    "key": "surroundings"
  },
  {
    "pt-pt": "os trabalhadores",
    "nl": "de arbeiders",
    "en": "workers",
    "fr": "les travailleurs",
    "de": "die Arbeiter",
    "it": "i lavoratori",
    "pl": "pracownicy",
    "pt-br": "os trabalhadores",
    "ro": "muncitorii",
    "ru": "работники",
    "es": "los trabajadores",
    "uk": "працівники",
    "word_type": "noun",
    "gender": "masculine",
    "key": "workers"
  },
  {
    "pt-pt": "a vítima",
    "nl": "het slachtoffer",
    "en": "victim",
    "fr": "la victime",
    "de": "das Opfer",
    "it": "la vittima",
    "pl": "ofiara",
    "pt-br": "a vítima",
    "ro": "victima",
    "ru": "жертва",
    "es": "la víctima",
    "uk": "жертва",
    "word_type": "noun",
    "plural_form": "as vítimas",
    "gender": "feminine",
    "key": "victim"
  },
  {
    "pt-pt": "o carnaval",
    "nl": "het carnaval",
    "en": "carnival",
    "fr": "le carnaval",
    "de": "der Karneval",
    "it": "il carnevale",
    "pl": "karnawał",
    "pt-br": "o carnaval",
    "ro": "carnavalul",
    "ru": "карнавал",
    "es": "el carnaval",
    "uk": "карнавал",
    "word_type": "noun",
    "plural_form": "os carnavais",
    "gender": "masculine",
    "key": "carnival"
  },
  {
    "pt-pt": "comercial",
    "nl": "commercieel",
    "en": "commercial",
    "fr": "commercial",
    "de": "kommerziell",
    "it": "commerciale",
    "pl": "handlowy",
    "pt-br": "comercial",
    "ro": "comercial",
    "ru": "коммерческий",
    "es": "comercial",
    "uk": "комерційний",
    "word_type": "adjective",
    "positive": "comercial",
    "comparative": "mais comercial",
    "superlative": "o mais comercial",
    "key": "commercial"
  },
  {
    "pt-pt": "a constituição",
    "nl": "de grondwet",
    "en": "constitution",
    "fr": "la constitution",
    "de": "die Verfassung",
    "it": "la costituzione",
    "pl": "konstytucja",
    "pt-br": "a constituição",
    "ro": "constituția",
    "ru": "конституция",
    "es": "la constitución",
    "uk": "конституція",
    "word_type": "noun",
    "plural_form": "as constituições",
    "gender": "feminine",
    "key": "constitution"
  },
  {
    "pt-pt": "o contrato",
    "nl": "het contract",
    "en": "contract",
    "fr": "le contrat",
    "de": "der Vertrag",
    "it": "il contratto",
    "pl": "umowa",
    "pt-br": "o contrato",
    "ro": "contractul",
    "ru": "контракт",
    "es": "el contrato",
    "uk": "контракт",
    "word_type": "noun",
    "plural_form": "os contratos",
    "gender": "masculine",
    "key": "contract"
  },
  {
    "pt-pt": "o documento",
    "nl": "het document",
    "en": "document",
    "fr": "le document",
    "de": "das Dokument",
    "it": "il documento",
    "pl": "dokument",
    "pt-br": "o documento",
    "ro": "documentul",
    "ru": "документ",
    "es": "el documento",
    "uk": "документ",
    "word_type": "noun",
    "gender": "masculine",
    "key": "document"
  },
  {
    "pt-pt": "a dúvida",
    "nl": "de twijfel",
    "en": "doubt",
    "fr": "le doute",
    "de": "der Zweifel",
    "it": "il dubbio",
    "pl": "wątpliwość",
    "pt-br": "a dúvida",
    "ro": "îndoiala",
    "ru": "сомнение",
    "es": "la duda",
    "uk": "сумнів",
    "word_type": "noun",
    "plural_form": "as dúvidas",
    "gender": "feminine",
    "key": "doubt"
  },
  {
    "pt-pt": "os jogadores",
    "nl": "de spelers",
    "en": "players",
    "fr": "les joueurs",
    "de": "die Spieler",
    "it": "i giocatori",
    "pl": "gracze",
    "pt-br": "os jogadores",
    "ro": "jucătorii",
    "ru": "игроки",
    "es": "los jugadores",
    "uk": "гравці",
    "word_type": "noun",
    "gender": "masculine",
    "key": "players"
  },
  {
    "pt-pt": "as meninas",
    "nl": "de meisjes",
    "en": "girls",
    "fr": "les filles",
    "de": "die Mädchen",
    "it": "le ragazze",
    "pl": "dziewczyny",
    "pt-br": "as meninas",
    "ro": "fetele",
    "ru": "девочки",
    "es": "las niñas",
    "uk": "дівчата",
    "word_type": "noun",
    "gender": "feminine",
    "key": "girls"
  },
  {
    "pt-pt": "naquele",
    "nl": "in dat",
    "en": "in that",
    "fr": "dans ce",
    "de": "in jenem",
    "it": "in quello",
    "pl": "w tamtym",
    "pt-br": "naquele",
    "ro": "în acel",
    "ru": "в том",
    "es": "en aquel",
    "uk": "в тому",
    "word_type": "pronoun",
    "key": "in-that"
  },
  {
    "pt-pt": "a violência",
    "nl": "het geweld",
    "en": "violence",
    "fr": "la violence",
    "de": "die Gewalt",
    "it": "la violenza",
    "pl": "przemoc",
    "pt-br": "a violência",
    "ro": "violența",
    "ru": "насилие",
    "es": "la violencia",
    "uk": "насильство",
    "word_type": "noun",
    "plural_form": "as violências",
    "gender": "feminine",
    "key": "violence"
  },
  {
    "pt-pt": "ótimo",
    "nl": "uitstekend",
    "en": "great",
    "fr": "excellent",
    "de": "großartig",
    "it": "ottimo",
    "pl": "świetny",
    "pt-br": "ótimo",
    "ro": "excelent",
    "ru": "отличный",
    "es": "óptimo",
    "uk": "чудовий",
    "word_type": "adjective",
    "positive": "ótimo",
    "comparative": "mais ótimo",
    "superlative": "o mais ótimo",
    "key": "great"
  },
  {
    "pt-pt": "adorar",
    "nl": "aanbidden",
    "en": "to adore",
    "fr": "adorer",
    "de": "verehren",
    "it": "adorare",
    "pl": "uwielbiać",
    "pt-br": "adorar",
    "ro": "a adora",
    "ru": "обожать",
    "es": "adorar",
    "uk": "обожнювати",
    "word_type": "verb",
    "first_person_singular": "eu adoro",
    "first_person_plural": "nós adoramos",
    "second_person_singular": "tu adoras",
    "second_person_plural": "vós adorais",
    "third_person_singular": "ele/ela adora",
    "third_person_plural": "eles/elas adoram",
    "key": "to-adore"
  },
  {
    "pt-pt": "as aulas",
    "nl": "de lessen",
    "en": "classes",
    "fr": "les cours",
    "de": "die Unterrichtsstunden",
    "it": "le lezioni",
    "pl": "lekcje",
    "pt-br": "as aulas",
    "ro": "lecțiile",
    "ru": "уроки",
    "es": "las clases",
    "uk": "уроки",
    "word_type": "noun",
    "gender": "feminine",
    "key": "classes"
  },
  {
    "pt-pt": "o comando",
    "nl": "de opdracht",
    "en": "command",
    "fr": "le commandement",
    "de": "das Kommando",
    "it": "il comando",
    "pl": "komenda",
    "pt-br": "o comando",
    "ro": "comanda",
    "ru": "команда",
    "es": "el mando",
    "uk": "команда",
    "word_type": "noun",
    "plural_form": "os comandos",
    "gender": "masculine",
    "key": "command"
  },
  {
    "pt-pt": "o destaque",
    "nl": "de uitblinker",
    "en": "highlight",
    "fr": "le point fort",
    "de": "das Highlight",
    "it": "il risalto",
    "pl": "wyróżnienie",
    "pt-br": "o destaque",
    "ro": "evidențierea",
    "ru": "выделение",
    "es": "el destaque",
    "uk": "виділення",
    "word_type": "noun",
    "plural_form": "os destaques",
    "gender": "masculine",
    "key": "highlight"
  },
  {
    "pt-pt": "a ligação",
    "nl": "de verbinding",
    "en": "connection",
    "fr": "la connexion",
    "de": "die Verbindung",
    "it": "il collegamento",
    "pl": "połączenie",
    "pt-br": "a ligação",
    "ro": "legătura",
    "ru": "связь",
    "es": "la conexión",
    "uk": "зв'язок",
    "word_type": "noun",
    "plural_form": "as ligações",
    "gender": "feminine",
    "key": "connection"
  },
  {
    "pt-pt": "procurar",
    "nl": "zoeken",
    "en": "to search",
    "fr": "chercher",
    "de": "suchen",
    "it": "cercare",
    "pl": "szukać",
    "pt-br": "procurar",
    "ro": "a căuta",
    "ru": "искать",
    "es": "buscar",
    "uk": "шукати",
    "word_type": "verb",
    "first_person_singular": "eu procuro",
    "first_person_plural": "nós procuramos",
    "second_person_singular": "tu procuras",
    "second_person_plural": "vós procurais",
    "third_person_singular": "ele/ela procura",
    "third_person_plural": "eles/elas procuram",
    "key": "to-search"
  },
  {
    "pt-pt": "proteger",
    "nl": "beschermen",
    "en": "to protect",
    "fr": "protéger",
    "de": "schützen",
    "it": "proteggere",
    "pl": "chronić",
    "pt-br": "proteger",
    "ro": "a proteja",
    "ru": "защищать",
    "es": "proteger",
    "uk": "захищати",
    "word_type": "verb",
    "first_person_singular": "eu protejo",
    "first_person_plural": "nós protegemos",
    "second_person_singular": "tu proteges",
    "second_person_plural": "vós protegeis",
    "third_person_singular": "ele/ela protege",
    "third_person_plural": "eles/elas protegem",
    "key": "to-protect"
  },
  {
    "pt-pt": "a referência",
    "nl": "de referentie",
    "en": "reference",
    "fr": "la référence",
    "de": "die Referenz",
    "it": "il riferimento",
    "pl": "odniesienie",
    "pt-br": "a referência",
    "ro": "referința",
    "ru": "ссылка",
    "es": "la referencia",
    "uk": "посилання",
    "word_type": "noun",
    "plural_form": "as referências",
    "gender": "feminine",
    "key": "reference"
  },
  {
    "pt-pt": "o solo",
    "nl": "de grond",
    "en": "ground",
    "fr": "le sol",
    "de": "der Boden",
    "it": "il suolo",
    "pl": "ziemia",
    "pt-br": "o solo",
    "ro": "solul",
    "ru": "почва",
    "es": "el suelo",
    "uk": "ґрунт",
    "word_type": "noun",
    "plural_form": "os solos",
    "gender": "masculine",
    "key": "ground"
  },
  {
    "pt-pt": "tradicional",
    "nl": "traditioneel",
    "en": "traditional",
    "fr": "traditionnel",
    "de": "traditionell",
    "it": "tradizionale",
    "pl": "tradycyjny",
    "pt-br": "tradicional",
    "ro": "tradițional",
    "ru": "традиционный",
    "es": "tradicional",
    "uk": "традиційний",
    "word_type": "adjective",
    "positive": "tradicional",
    "comparative": "mais tradicional",
    "superlative": "o mais tradicional",
    "key": "traditional"
  },
  {
    "pt-pt": "assistir",
    "nl": "bijwonen",
    "en": "to watch",
    "fr": "regarder",
    "de": "zusehen",
    "it": "guardare",
    "pl": "oglądać",
    "pt-br": "assistir",
    "ro": "a asista",
    "ru": "смотреть",
    "es": "ver",
    "uk": "дивитися",
    "word_type": "verb",
    "first_person_singular": "eu assisto",
    "first_person_plural": "nós assistimos",
    "second_person_singular": "tu assistes",
    "second_person_plural": "vós assistis",
    "third_person_singular": "ele/ela assiste",
    "third_person_plural": "eles/elas assistem",
    "key": "to-watch"
  },
  {
    "pt-pt": "descobrir",
    "nl": "ontdekken",
    "en": "to discover",
    "fr": "découvrir",
    "de": "entdecken",
    "it": "scoprire",
    "pl": "odkrywać",
    "pt-br": "descobrir",
    "ro": "a descoperi",
    "ru": "открывать",
    "es": "descubrir",
    "uk": "відкривати",
    "word_type": "verb",
    "first_person_singular": "eu descubro",
    "first_person_plural": "nós descobrimos",
    "second_person_singular": "tu descobres",
    "second_person_plural": "vós descobris",
    "third_person_singular": "ele/ela descobre",
    "third_person_plural": "eles/elas descobrem",
    "key": "to-discover"
  },
  {
    "pt-pt": "o horário",
    "nl": "het rooster",
    "en": "schedule",
    "fr": "l'horaire",
    "de": "der Zeitplan",
    "it": "l'orario",
    "pl": "rozkład",
    "pt-br": "o horário",
    "ro": "orarul",
    "ru": "расписание",
    "es": "el horario",
    "uk": "розклад",
    "word_type": "noun",
    "plural_form": "os horários",
    "gender": "masculine",
    "key": "schedule"
  },
  {
    "pt-pt": "o mestre",
    "nl": "de meester",
    "en": "master",
    "fr": "le maître",
    "de": "der Meister",
    "it": "il maestro",
    "pl": "mistrz",
    "pt-br": "o mestre",
    "ro": "maestrul",
    "ru": "мастер",
    "es": "el maestro",
    "uk": "майстер",
    "word_type": "noun",
    "plural_form": "os mestres",
    "gender": "masculine",
    "key": "master"
  },
  {
    "pt-pt": "o padrão",
    "nl": "het patroon",
    "en": "pattern",
    "fr": "le modèle",
    "de": "das Muster",
    "it": "il modello",
    "pl": "wzór",
    "pt-br": "o padrão",
    "ro": "modelul",
    "ru": "образец",
    "es": "el patrón",
    "uk": "зразок",
    "word_type": "noun",
    "plural_form": "os padrões",
    "gender": "masculine",
    "key": "pattern"
  },
  {
    "pt-pt": "o prazer",
    "nl": "het plezier",
    "en": "pleasure",
    "fr": "le plaisir",
    "de": "das Vergnügen",
    "it": "il piacere",
    "pl": "przyjemność",
    "pt-br": "o prazer",
    "ro": "plăcerea",
    "ru": "удовольствие",
    "es": "el placer",
    "uk": "задоволення",
    "word_type": "noun",
    "plural_form": "os prazeres",
    "gender": "masculine",
    "key": "pleasure"
  },
  {
    "pt-pt": "a prefeitura",
    "nl": "het gemeentehuis",
    "en": "city hall",
    "fr": "la mairie",
    "de": "das Rathaus",
    "it": "il municipio",
    "pl": "ratusz",
    "pt-br": "a prefeitura",
    "ro": "primăria",
    "ru": "мэрия",
    "es": "el ayuntamiento",
    "uk": "мерія",
    "word_type": "noun",
    "plural_form": "as prefeituras",
    "gender": "feminine",
    "key": "city-hall"
  },
  {
    "pt-pt": "a reforma",
    "nl": "de hervorming",
    "en": "reform",
    "fr": "la réforme",
    "de": "die Reform",
    "it": "la riforma",
    "pl": "reforma",
    "pt-br": "a reforma",
    "ro": "reforma",
    "ru": "реформа",
    "es": "la reforma",
    "uk": "реформа",
    "word_type": "noun",
    "plural_form": "as reformas",
    "gender": "feminine",
    "key": "reform"
  },
  {
    "pt-pt": "representar",
    "nl": "vertegenwoordigen",
    "en": "to represent",
    "fr": "représenter",
    "de": "vertreten",
    "it": "rappresentare",
    "pl": "reprezentować",
    "pt-br": "representar",
    "ro": "a reprezenta",
    "ru": "представлять",
    "es": "representar",
    "uk": "представляти",
    "word_type": "verb",
    "first_person_singular": "eu represento",
    "first_person_plural": "nós representamos",
    "second_person_singular": "tu representas",
    "second_person_plural": "vós representais",
    "third_person_singular": "ele/ela representa",
    "third_person_plural": "eles/elas representam",
    "key": "to-represent"
  },
  {
    "pt-pt": "resolver",
    "nl": "oplossen",
    "en": "to solve",
    "fr": "résoudre",
    "de": "lösen",
    "it": "risolvere",
    "pl": "rozwiązywać",
    "pt-br": "resolver",
    "ro": "a rezolva",
    "ru": "решать",
    "es": "resolver",
    "uk": "вирішувати",
    "word_type": "verb",
    "first_person_singular": "eu resolvo",
    "first_person_plural": "nós resolvemos",
    "second_person_singular": "tu resolves",
    "second_person_plural": "vós resolveis",
    "third_person_singular": "ele/ela resolve",
    "third_person_plural": "eles/elas resolvem",
    "key": "to-solve"
  },
  {
    "pt-pt": "o tiro",
    "nl": "het schot",
    "en": "shot",
    "fr": "le tir",
    "de": "der Schuss",
    "it": "il tiro",
    "pl": "strzał",
    "pt-br": "o tiro",
    "ro": "focul",
    "ru": "выстрел",
    "es": "el tiro",
    "uk": "постріл",
    "word_type": "noun",
    "plural_form": "os tiros",
    "gender": "masculine",
    "key": "shot"
  },
  {
    "pt-pt": "a velocidade",
    "nl": "de snelheid",
    "en": "speed",
    "fr": "la vitesse",
    "de": "die Geschwindigkeit",
    "it": "la velocità",
    "pl": "prędkość",
    "pt-br": "a velocidade",
    "ro": "viteza",
    "ru": "скорость",
    "es": "la velocidad",
    "uk": "швидкість",
    "word_type": "noun",
    "plural_form": "as velocidades",
    "gender": "feminine",
    "key": "speed"
  },
  {
    "pt-pt": "diretamente",
    "nl": "direct",
    "en": "directly",
    "fr": "directement",
    "de": "direkt",
    "it": "direttamente",
    "pl": "bezpośrednio",
    "pt-br": "diretamente",
    "ro": "direct",
    "ru": "напрямую",
    "es": "directamente",
    "uk": "безпосередньо",
    "word_type": "adverb",
    "key": "directly"
  }
]